[
  {
    "nama": "John Doe",
    "nik_kk": "1234567890123456",
    "nik": "3210987654321098",
    "jenis_kelamin": "L",
    "status_perkawinan": "Belum Kawin",
    "tempat_lahir": "Jakarta",
    "tanggal_lahir": "1990-01-01",
    "pendidikan_terakhir": "S1",
    "pekerjaan": "Karyawan Swasta",
    "alamat_lengkap": "Jl. Merdeka No. 1, Jakarta",
    "kedudukan_dalam_keluarga": "Anak",
    "nama_ibu_kandung": "Jane Doe"
  },
  {
    "nama": "Jane Smith",
    "nik_kk": "2345678901234567",
    "nik": "4321098765432109",
    "jenis_kelamin": "P",
    "status_perkawinan": "Kawin",
    "tempat_lahir": "Bandung",
    "tanggal_lahir": "1985-05-05",
    "pendidikan_terakhir": "S2",
    "pekerjaan": "Dosen",
    "alamat_lengkap": "Jl. Sudirman No. 2, Bandung",
    "kedudukan_dalam_keluarga": "Istri",
    "nama_ibu_kandung": "Mary Smith"
  },
  {
    "nama": "Michael Johnson",
    "nik_kk": "3456789012345678",
    "nik": "5432109876543210",
    "jenis_kelamin": "L",
    "status_perkawinan": "Kawin",
    "tempat_lahir": "Surabaya",
    "tanggal_lahir": "1978-08-08",
    "pendidikan_terakhir": "SMA",
    "pekerjaan": "Pengusaha",
    "alamat_lengkap": "Jl. Diponegoro No. 3, Surabaya",
    "kedudukan_dalam_keluarga": "Suami",
    "nama_ibu_kandung": "Anna Johnson"
  },
  {
    "nama": "Emily Davis",
    "nik_kk": "4567890123456789",
    "nik": "6543210987654321",
    "jenis_kelamin": "P",
    "status_perkawinan": "Janda",
    "tempat_lahir": "Medan",
    "tanggal_lahir": "1992-12-12",
    "pendidikan_terakhir": "D3",
    "pekerjaan": "Perawat",
    "alamat_lengkap": "Jl. Hasanuddin No. 4, Medan",
    "kedudukan_dalam_keluarga": "Anak",
    "nama_ibu_kandung": "Lisa Davis"
  },
  {
    "nama": "David Brown",
    "nik_kk": "5678901234567890",
    "nik": "7654321098765432",
    "jenis_kelamin": "L",
    "status_perkawinan": "Duda",
    "tempat_lahir": "Yogyakarta",
    "tanggal_lahir": "1980-03-03",
    "pendidikan_terakhir": "SMA",
    "pekerjaan": "Petani",
    "alamat_lengkap": "Jl. Malioboro No. 5, Yogyakarta",
    "kedudukan_dalam_keluarga": "Ayah",
    "nama_ibu_kandung": "Nancy Brown"
  }
]
